{
  "command": [
    "/home/matt/Desktop/ray/aide-parallel-public/cli/aide-run",
    "--task",
    "algotune",
    "--at-task",
    "generalized_eigenvalues_real",
    "--num-experiments",
    "4",
    "--num-iterations",
    "1",
    "--steps",
    "4",
    "--cpus-per-experiment",
    "2",
    "--at-n-problems",
    "5",
    "--at-n-runs",
    "3",
    "--result-json",
    "/home/matt/Desktop/ray/aide-parallel-public/runs/algotune/full-algotune-ray-coverage-groq/tasks/generalized_eigenvalues_real/result.json",
    "--at-fast",
    "--local",
    "--model",
    "llama-3.3-70b-versatile",
    "--feedback-model",
    "llama-3.3-70b-versatile"
  ],
  "config_hash": "43dcdfc98f21",
  "error": "The actor died unexpectedly before finishing this task.\n\tclass_name: Experiment\n\tactor_id: d4b6dc01cd08cb99cb33e55304000000\n\tpid: 2132852\n\tnamespace: 5758d647-a8c6-4ec1-8c67-c84d08ce8f0c\n\tip: 192.168.0.105\nThe actor is dead because its owner has died. Owner Id: 04000000ffffffffffffffffffffffffffffffffffffffffffffffff Owner Ip address: 192.168.0.105 Owner worker exit type: SYSTEM_ERROR Worker exit detail: Owner's node has crashed.",
  "returncode": 1,
  "status": "failed",
  "task_id": "generalized_eigenvalues_real",
  "task_type": "algotune"
}